openai_core/__init__.py
openai_core-0.0.1.dist-info/METADATA
openai_core-0.0.1.dist-info/WHEEL
openai_core-0.0.1.dist-info/RECORD
