Metadata-Version: 2.1
Name: openai-core
Version: 0.0.1
Requires-Dist: aiohttp
Requires-Dist: jsonschema
Requires-Dist: requests
